pymultifracs/__init__.py
pymultifracs/_version.py
pymultifracs/autorange.py
pymultifracs/bootstrap.py
pymultifracs/estimation.py
pymultifracs/mf_analysis.py
pymultifracs/multiresquantity.py
pymultifracs/regression.py
pymultifracs/scalingfunction.py
pymultifracs/surrogate.py
pymultifracs/utils.py
pymultifracs/viz.py
pymultifracs/wavelet.py
pymultifracs/bivariate/__init__.py
pymultifracs/bivariate/bimfa.py
pymultifracs/bivariate/biscaling_function.py
pymultifracs/cwt/c-mfa.py
pymultifracs/robust/Pelt.py
pymultifracs/robust/__init__.py
pymultifracs/robust/benchmark.py
pymultifracs/robust/hilbert.py
pymultifracs/robust/robust.py
pymultifracs/robust/segmentation.py
pymultifracs/simul/__init__.py
pymultifracs/simul/fbm.py
pymultifracs/simul/mrw.py
pymultifracs/simul/noisy.py
pymultifracs/simul/pzutils.py
pymultifracs-0.3.1.dist-info/licenses/LICENSE
pymultifracs-0.3.1.dist-info/METADATA
pymultifracs-0.3.1.dist-info/WHEEL
pymultifracs-0.3.1.dist-info/top_level.txt
pymultifracs-0.3.1.dist-info/RECORD
