Metadata-Version: 2.4
Name: pymultifracs
Version: 0.3.1
Summary: Implements wavelet based multifractal analysis of 1d signals.
Author: Merlin Dumeur, Omar Darwiche Domingues, Roberto Fabio Leonarduzzi
License-Expression: MIT
Project-URL: Documentation, https://www.neurospin.fr/pymultifracs/
Project-URL: Source, https://github.com/neurospin/pymultifracs
Project-URL: Tracker, https://github.com/neurospin/pymultifracs/issues/
Classifier: Intended Audience :: Science/Research
Classifier: Intended Audience :: Developers
Classifier: Programming Language :: Python :: 3
Classifier: Topic :: Software Development
Classifier: Topic :: Scientific/Engineering
Classifier: Operating System :: OS Independent
Requires-Python: >=3.10
License-File: LICENSE
Requires-Dist: numpy
Requires-Dist: scipy
Requires-Dist: pywavelets
Requires-Dist: seaborn
Requires-Dist: xarray
Provides-Extra: bootstrap
Requires-Dist: recombinator; extra == "bootstrap"
Provides-Extra: robust
Requires-Dist: statsmodels; extra == "robust"
Requires-Dist: ruptures; extra == "robust"
Requires-Dist: numba; extra == "robust"
Requires-Dist: tqdm; extra == "robust"
Provides-Extra: full
Requires-Dist: pymultifracs[bootstrap,robust]; extra == "full"
Provides-Extra: test
Requires-Dist: pytest; extra == "test"
Requires-Dist: pytest-xdist; extra == "test"
Requires-Dist: pytest-cov; extra == "test"
Requires-Dist: statsmodels; extra == "test"
Requires-Dist: recombinator; extra == "test"
Requires-Dist: joblib; extra == "test"
Provides-Extra: doc
Requires-Dist: sphinx; extra == "doc"
Requires-Dist: numpydoc; extra == "doc"
Requires-Dist: pydata-sphinx-theme; extra == "doc"
Requires-Dist: sphinx-gallery; extra == "doc"
Requires-Dist: joblib; extra == "doc"
Requires-Dist: pooch; extra == "doc"
Requires-Dist: myst-parser; extra == "doc"
Provides-Extra: dev
Requires-Dist: pymultifracs[bootstrap,doc,robust,test]; extra == "dev"
Dynamic: license-file
